winmailopenapi/Base.py
winmailopenapi/OpenApi.py
winmailopenapi/__init__.py
winmailopenapi/resources/__init__.py
winmailopenapi/resources/admin/__init__.py
winmailopenapi/resources/admin/adminuser.py
winmailopenapi/resources/admin/domain.py
winmailopenapi/resources/admin/domainalias.py
winmailopenapi/resources/admin/group.py
winmailopenapi/resources/admin/user.py
winmailopenapi/resources/admin/useralias.py
winmailopenapi/resources/user/__init__.py
winmailopenapi/resources/user/addressbook.py
winmailopenapi/resources/user/folders.py
winmailopenapi/resources/user/msglist.py
winmailopenapi/resources/user/msgnum.py
winmailopenapi/resources/user/netaddressbook.py
winmailopenapi/resources/user/newmsg.py
winmailopenapi/resources/user/readmsg.py
winmailopenapi/resources/user/systemgroup.py
winmailopenapi/resources/user/upload.py
winmailopenapi/utils/__init__.py
winmailopenapi/utils/utils.py
winmailopenapi-2025.7.16.dist-info/METADATA
winmailopenapi-2025.7.16.dist-info/WHEEL
winmailopenapi-2025.7.16.dist-info/top_level.txt
winmailopenapi-2025.7.16.dist-info/RECORD
