Metadata-Version: 2.1
Name: winmailopenapi
Version: 2025.7.16
Summary: Winmail OpenApi
Home-page: http://winmail.cn
Author: Sway
Author-email: sway_wang@foxmail.com
License: UNKNOWN
Platform: UNKNOWN
Requires-Python: >=3.6.0
Requires-Dist: requests
Requires-Dist: pydantic
